llm_tools_skills/__init__.py
llm_tools_skills/toolbox.py
llm_tools_skills-0.2.0.dist-info/METADATA
llm_tools_skills-0.2.0.dist-info/WHEEL
llm_tools_skills-0.2.0.dist-info/entry_points.txt
llm_tools_skills-0.2.0.dist-info/top_level.txt
llm_tools_skills-0.2.0.dist-info/RECORD
