Metadata-Version: 2.4
Name: llm-tools-skills
Version: 0.2.0
Summary: Add Skills bundles to the LLM CLI tool
Author-email: Dane Summers <dsummersl@gmail.com>
License: Apache-2.0
Classifier: Programming Language :: Python :: 3
Classifier: License :: OSI Approved
Classifier: Typing :: Typed
Requires-Python: >=3.11
Requires-Dist: llm>=0.27.1
